netzero/__init__.py
netzero/__main__.py
netzero/collect.py
netzero/config.py
netzero/db.py
netzero/dirs.py
netzero/format.py
netzero/sources.py
netzero/util.py
netzero/builtin/__init__.py
netzero/builtin/gshp.py
netzero/builtin/pepco.py
netzero/builtin/solar.py
netzero/builtin/weather.py
netzero-0.1.0.dist-info/LICENSE
netzero-0.1.0.dist-info/METADATA
netzero-0.1.0.dist-info/WHEEL
netzero-0.1.0.dist-info/entry_points.txt
netzero-0.1.0.dist-info/top_level.txt
netzero-0.1.0.dist-info/RECORD
