Metadata-Version: 2.1
Name: netzero
Version: 0.1.0
Summary: A collection of tools to mine data on the efficiency of a house
Home-page: https://github.com/RobMor/NetZero
Author: Robert Morrison
Author-email: robbieguy98@gmail.com
License: UNKNOWN
Platform: UNKNOWN
Classifier: Programming Language :: Python :: 3
Classifier: License :: OSI Approved :: MIT License
Classifier: Operating System :: OS Independent
Requires-Python: >=3.6
Requires-Dist: requests
Requires-Dist: bs4
Requires-Dist: entrypoints
